{
    "mass": 1800.0,
    "principal_moments_of_inertia": [2000.0, 750.0, 2400.0],
    "max_power": 113000.0,
    "max_torque": 380.0,
    "max_speed": 50.0,
    "wheel_common": {
        "radius": 0.44,
        "width": 0.32,
        "mass": 25.0,
        "moment_of_inertia": 3.6,
        "hardness": [24000.0, 8000.0],
        "damping": 2400.0,
        "travel": 2.0,
        "texture_center": [190.0, 221.0],
        "texture_radius": 49.0
    },
    "wheels": [
        {
            "center": [-1.0, 1.97, -0.88]
        },
        {
            "center": [1.0, 1.97, -0.88]
        },
        {
            "center": [1.0, -1.36, -0.88]
        },
        {
            "center": [-1.0, -1.36, -0.88]
        }
    ]
}